{
  "1": [
    {
      "date": "2025/08/01-10R",
      "report": "● 출발 후 약 200m 지점부터 3코너 지점까지 ⑥”트리플신화“는 앞선 말의 페이스가 느려 기승기수 이성재가 말을 제어하는 과정에서 머리를 드는 등 주행이 좋지 못하였음.",
      "hrName": "트리플신화"
    }
  ],
  "트리플신화": [
    {
      "date": "2025/08/01-10R",
      "report": "● 출발 후 약 200m 지점부터 3코너 지점까지 ⑥”트리플신화“는 앞선 말의 페이스가 느려 기승기수 이성재가 말을 제어하는 과정에서 머리를 드는 등 주행이 좋지 못하였음.",
      "hrName": "트리플신화"
    }
  ],
  "2": [
    {
      "date": "2025/08/29-8R",
      "report": "● 출전표 공표 후 동 경주의 부담중량 오류를 정정하는 과정에서 ③“블랙팰컨”의 부담중량이 당초 54.0kg에서 53.5kg으로 변경되었고, 심판위원은 해당 부담중량으로 기승이 어렵다는 기승기수 다나카의 요청사항을 받아들여 53.5kg에서 54.0kg으로 초과중량(+500g) 기승을 허용.\n● 결승선 전방 약 200m 지점에서 ③“블랙팰컨”은 바깥으로 기댔음.",
      "hrName": "블랙팰컨"
    }
  ],
  "블랙팰컨": [
    {
      "date": "2025/08/29-8R",
      "report": "● 출전표 공표 후 동 경주의 부담중량 오류를 정정하는 과정에서 ③“블랙팰컨”의 부담중량이 당초 54.0kg에서 53.5kg으로 변경되었고, 심판위원은 해당 부담중량으로 기승이 어렵다는 기승기수 다나카의 요청사항을 받아들여 53.5kg에서 54.0kg으로 초과중량(+500g) 기승을 허용.\n● 결승선 전방 약 200m 지점에서 ③“블랙팰컨”은 바깥으로 기댔음.",
      "hrName": "블랙팰컨"
    }
  ],
  "3": [
    {
      "date": "2025/12/19-8R",
      "report": "● 출발 시 ⑫“탐라슈퍼”는 앞다리를 들며 바깥으로 기대며 나갔음.",
      "hrName": "탐라슈퍼"
    }
  ],
  "탐라슈퍼": [
    {
      "date": "2025/12/19-8R",
      "report": "● 출발 시 ⑫“탐라슈퍼”는 앞다리를 들며 바깥으로 기대며 나갔음.",
      "hrName": "탐라슈퍼"
    }
  ],
  "4": [
    {
      "date": "2026/01/09-2R",
      "report": "● 1코너 중반부터 3코너 진입지점까지 ①“닥터크리스”는 기승기수 진겸의 제어 노력에도 불구하고 끌며 머리를 드는 등 주행이 좋지 못하였음.\n● [미입상 인기마 기승기수 인터뷰] ①“닥터크리스”(단승식 인기 1위(배당률 1.8), 경주결과 6위) 기승기수 진겸은 경주 작전은 편안하게 선행을 가거나 그렇지 못할 경우 선입권에 자리를 잡는 것이었는데, 출발이 밋밋하였고, 상대적으로 바깥쪽 말들이 빨라 선입권에 자리를 잡았다고 진술. 이후 1코너 중반 지점부터 말을 제어하는 과정에서 동 말이 상대적으로 크고 보폭도 큰 말인데 선두권의 페이스가 느리고 말이 끌어 제어가 원활하지 못하였고, 이후 3코너 진입지점까지 말을 제어하는 과정에서 말의 체력이 소진된 점이 성적이 좋지 못한 주된 원인인 것 같다고 진술.",
      "hrName": "닥터크리스"
    }
  ],
  "닥터크리스": [
    {
      "date": "2026/01/09-2R",
      "report": "● 1코너 중반부터 3코너 진입지점까지 ①“닥터크리스”는 기승기수 진겸의 제어 노력에도 불구하고 끌며 머리를 드는 등 주행이 좋지 못하였음.\n● [미입상 인기마 기승기수 인터뷰] ①“닥터크리스”(단승식 인기 1위(배당률 1.8), 경주결과 6위) 기승기수 진겸은 경주 작전은 편안하게 선행을 가거나 그렇지 못할 경우 선입권에 자리를 잡는 것이었는데, 출발이 밋밋하였고, 상대적으로 바깥쪽 말들이 빨라 선입권에 자리를 잡았다고 진술. 이후 1코너 중반 지점부터 말을 제어하는 과정에서 동 말이 상대적으로 크고 보폭도 큰 말인데 선두권의 페이스가 느리고 말이 끌어 제어가 원활하지 못하였고, 이후 3코너 진입지점까지 말을 제어하는 과정에서 말의 체력이 소진된 점이 성적이 좋지 못한 주된 원인인 것 같다고 진술.",
      "hrName": "닥터크리스"
    }
  ],
  "5": [
    {
      "date": "2026/02/15-7R",
      "report": "● 경주 후 ⑪“더베스트에버”에 대해 마체검사 지정. 수의위원의 검사결과 오른 앞다리 절음이 확인됨.",
      "hrName": "더베스트에버"
    }
  ],
  "더베스트에버": [
    {
      "date": "2026/02/15-7R",
      "report": "● 경주 후 ⑪“더베스트에버”에 대해 마체검사 지정. 수의위원의 검사결과 오른 앞다리 절음이 확인됨.",
      "hrName": "더베스트에버"
    }
  ],
  "6": [
    {
      "date": "2026/01/09-9R",
      "report": "● 출발 시 ①“볼프스킹맨”은 안으로 기대며 출발이 늦었음.",
      "hrName": "볼프스킹맨"
    }
  ],
  "볼프스킹맨": [
    {
      "date": "2026/01/09-9R",
      "report": "● 출발 시 ①“볼프스킹맨”은 안으로 기대며 출발이 늦었음.",
      "hrName": "볼프스킹맨"
    }
  ],
  "7": [
    {
      "date": "2026/01/18-5R",
      "report": "● 출발 시 ①“크레이지아미”는 출발이 늦었음.",
      "hrName": "크레이지아미"
    }
  ],
  "크레이지아미": [
    {
      "date": "2026/01/18-5R",
      "report": "● 출발 시 ①“크레이지아미”는 출발이 늦었음.",
      "hrName": "크레이지아미"
    }
  ],
  "8": [
    {
      "date": "2026/02/15-7R",
      "report": "● 출발부터 2코너 지점까지 ⑤“원대한꿈”은 머리를 들며 안팎으로 기대는 등 주행이 불안하였음.",
      "hrName": "원대한꿈"
    }
  ],
  "원대한꿈": [
    {
      "date": "2026/02/15-7R",
      "report": "● 출발부터 2코너 지점까지 ⑤“원대한꿈”은 머리를 들며 안팎으로 기대는 등 주행이 불안하였음.",
      "hrName": "원대한꿈"
    }
  ],
  "9": [
    {
      "date": "2026/01/23-8R",
      "report": "● 3코너 지점에서 ⑧“바이스로열”은 일시적으로 끌며 바깥으로 기대며 나갔음.",
      "hrName": "바이스로열"
    }
  ],
  "바이스로열": [
    {
      "date": "2026/01/23-8R",
      "report": "● 3코너 지점에서 ⑧“바이스로열”은 일시적으로 끌며 바깥으로 기대며 나갔음.",
      "hrName": "바이스로열"
    }
  ],
  "10": [
    {
      "date": "2026/01/02-7R",
      "report": "● 경주 후 ⑧“운주위너”에 대해 마체검사 지정. 수의위원의 검사결과 오른 앞다리 절음이 확인됨.",
      "hrName": "운주위너"
    }
  ],
  "운주위너": [
    {
      "date": "2026/01/02-7R",
      "report": "● 경주 후 ⑧“운주위너”에 대해 마체검사 지정. 수의위원의 검사결과 오른 앞다리 절음이 확인됨.",
      "hrName": "운주위너"
    }
  ],
  "11": [
    {
      "date": "2026/01/23-8R",
      "report": "● 출발 시 ⑤“아너드칸”은 출발이 늦었음.",
      "hrName": "아너드칸"
    }
  ],
  "아너드칸": [
    {
      "date": "2026/01/23-8R",
      "report": "● 출발 시 ⑤“아너드칸”은 출발이 늦었음.",
      "hrName": "아너드칸"
    }
  ],
  "12": [
    {
      "date": "2025/05/25-6R",
      "report": "● 경주 결과 ⑩“벌마의영웅”의 성적이 예상보다 저조했던 것에 대해, 기승기수 다나카는 경주 작전은 출발이 빠른 말이 없어 앞선에 위치하는 것이었고 계획대로 선입권에 자리를 잡았으며, 1-2코너에서는 페이스가 다소 빨랐지만 건너편 직선주로에서는 페이스가 느려져 다소 제어하며 주행하였다고 진술. 이후 4코너 지점까지도 앞선에서 주행하였으나 결승선 전방 약 200m 지점부터는 동 말의 탄력이 떨어졌는데, 경주 초반 페이스가 빨랐던 점과 출발대 번호가 바깥이어서 경주 중 외곽으로 주행한 점, 동 말이 장기간 휴양 후 첫 출전이어서 경주 감각이 떨어진 점이 경주결과에 영향을 미친 것 같다고 진술.",
      "hrName": "벌마의영웅"
    }
  ],
  "벌마의영웅": [
    {
      "date": "2025/05/25-6R",
      "report": "● 경주 결과 ⑩“벌마의영웅”의 성적이 예상보다 저조했던 것에 대해, 기승기수 다나카는 경주 작전은 출발이 빠른 말이 없어 앞선에 위치하는 것이었고 계획대로 선입권에 자리를 잡았으며, 1-2코너에서는 페이스가 다소 빨랐지만 건너편 직선주로에서는 페이스가 느려져 다소 제어하며 주행하였다고 진술. 이후 4코너 지점까지도 앞선에서 주행하였으나 결승선 전방 약 200m 지점부터는 동 말의 탄력이 떨어졌는데, 경주 초반 페이스가 빨랐던 점과 출발대 번호가 바깥이어서 경주 중 외곽으로 주행한 점, 동 말이 장기간 휴양 후 첫 출전이어서 경주 감각이 떨어진 점이 경주결과에 영향을 미친 것 같다고 진술.",
      "hrName": "벌마의영웅"
    }
  ]
}